{
  "objectInfo" : {
    "id" : "3FRb8zmTcATdNaP3RltNYh",
    "name" : "BulkUnlink_LTF_Mapping_Task",
    "type" : "MTT",
    "metadata" : {
      "modelVersion" : {
        "major" : 0,
        "minor" : 0
      },
      "repoInfo" : {
        "repoHandle" : "01005E0Z000000000CYF"
      },
      "contextAttributes" : [ {
        "name" : "id",
        "value" : "@1"
      } ],
      "additionalInfo" : {
        "description" : "",
        "contentType" : "JSON",
        "documentState" : "VALID"
      }
    }
  },
  "dataFileExtension" : "zip",
  "objectRefs" : [ {
    "id" : "26JhsMK3EqcdSWknjIed4J",
    "name" : "BulkUnlink_LTF_Mapping",
    "type" : "DTEMPLATE",
    "metadata" : {
      "modelVersion" : {
        "major" : 0,
        "minor" : 0
      },
      "repoInfo" : {
        "repoHandle" : "01005E1700000000061O"
      },
      "contextAttributes" : [ {
        "name" : "id",
        "value" : "@1"
      } ],
      "additionalInfo" : {
        "description" : "",
        "contentType" : "JSON",
        "documentState" : "VALID"
      }
    },
    "path" : "/Explore/BulkUnlinkTestProj3/BulkUnlink_FOLDER"
  }, {
    "id" : "8dZv845FBmzd6ZLYNRWGG5",
    "name" : "FF_PodCertification",
    "type" : "Connection",
    "metadata" : {
      "modelVersion" : {
        "major" : 0,
        "minor" : 0
      },
      "repoInfo" : {
        "repoHandle" : "01005E0B000000000A2Z"
      },
      "contextAttributes" : null,
      "additionalInfo" : {
        "description" : "Flat File connection for Pod Certification Automation",
        "contentType" : "JSON",
        "documentState" : "COMPLETE"
      }
    },
    "path" : "/SYS"
  }, {
    "id" : "2jwbGpnbeeqeOL6I9aWWyI",
    "name" : "TMS47W1264001",
    "type" : "AgentGroup",
    "metadata" : {
      "modelVersion" : {
        "major" : 0,
        "minor" : 0
      },
      "repoInfo" : {
        "repoHandle" : "01005E25000000000008"
      },
      "contextAttributes" : null,
      "additionalInfo" : {
        "description" : null,
        "contentType" : "JSON",
        "documentState" : "VALID"
      }
    },
    "path" : "/SYS"
  } ]
}